{
  "word": "senocular",
  "etymologies": [
    {
      "description": [
        "From Latin sēnī (“six each”), from sex (“six”) + oculus (“eye”)."
      ],
      "adjectives": [
        {
          "description": "senocular (not comparable)",
          "definitionGroups": [
            {
              "group": null,
              "entries": [
                {
                  "meaning": "Having six eyes.",
                  "examples": []
                }
              ]
            }
          ]
        }
      ],
      "adverbs": [],
      "nouns": [],
      "prepositions": [],
      "verbs": [],
      "letter": [],
      "number": []
    }
  ]
}