{
  "word": "constituently",
  "etymologies": [
    {
      "description": [
        "constituent +‎ -ly"
      ],
      "adjectives": [],
      "adverbs": [
        {
          "description": "constituently (not comparable)",
          "definitionGroups": [
            {
              "group": null,
              "entries": [
                {
                  "meaning": "In terms of the constituents of a mixture.",
                  "examples": []
                }
              ]
            }
          ]
        }
      ],
      "nouns": [],
      "prepositions": [],
      "verbs": [],
      "letter": [],
      "number": []
    }
  ]
}