{
  "word": "pejorate",
  "etymologies": [
    {
      "description": [
        "From (the participle stem of) Latin peiorō (“make worse”), from pēior (“worse”)."
      ],
      "adjectives": [],
      "adverbs": [],
      "nouns": [],
      "prepositions": [],
      "verbs": [
        {
          "description": "pejorate (third-person singular simple present pejorates, present participle pejorating, simple past and past participle pejorated)",
          "definitionGroups": [
            {
              "group": null,
              "entries": [
                {
                  "meaning": "(transitive, intransitive) To make or become worse; to deteriorate or to worsen.",
                  "examples": []
                }
              ]
            }
          ]
        }
      ]
    }
  ]
}