{
  "word": "engulf",
  "etymologies": [
    {
      "description": [
        "en- +‎ gulf"
      ],
      "adjectives": [],
      "adverbs": [],
      "nouns": [],
      "prepositions": [],
      "verbs": [
        {
          "description": "engulf (third-person singular simple present engulfs, present participle engulfing, simple past and past participle engulfed)",
          "definitionGroups": [
            {
              "group": null,
              "entries": [
                {
                  "meaning": "(transitive) To overwhelm.",
                  "examples": [
                    "Desperation engulfed her after her daughter's death."
                  ]
                }
              ]
            },
            {
              "group": null,
              "entries": [
                {
                  "meaning": "(transitive) To surround; to cover; to submerge.",
                  "examples": [
                    "Only Noah and his family survived when the Flood engulfed the world."
                  ]
                }
              ]
            },
            {
              "group": null,
              "entries": [
                {
                  "meaning": "(transitive) To cast into a gulf.",
                  "examples": []
                }
              ]
            }
          ]
        }
      ],
      "letter": [],
      "number": []
    }
  ]
}