{
  "word": "confutable",
  "etymologies": [
    {
      "description": [
        "confute +‎ -able"
      ],
      "adjectives": [
        {
          "description": "confutable (not comparable)",
          "definitionGroups": [
            {
              "group": null,
              "entries": [
                {
                  "meaning": "(archaic or formal) That can be confuted, i.e. shown to be false; disprovable.",
                  "examples": [
                    "That Caucasus enjoys the Sunbeams three parts of the Nights Vigils; that Danubius ariseth from the Pyrenæan Hills: That the Earth is higher towards the North: are opinions truly charged on Aristotle by the Restorer of Epicurus; and all easily confutable falsities."
                  ]
                }
              ]
            }
          ]
        }
      ],
      "adverbs": [],
      "nouns": [],
      "prepositions": [],
      "verbs": [],
      "letter": [],
      "number": []
    }
  ]
}