{
  "word": "unbinding",
  "etymologies": [
    {
      "description": [],
      "adjectives": [],
      "adverbs": [],
      "nouns": [
        {
          "description": "unbinding (plural unbindings)",
          "definitionGroups": [
            {
              "group": null,
              "entries": [
                {
                  "meaning": "The release or freeing of something that was bound.",
                  "examples": []
                }
              ]
            }
          ]
        }
      ],
      "prepositions": [],
      "verbs": [
        {
          "description": "unbinding",
          "definitionGroups": [
            {
              "group": null,
              "entries": [
                {
                  "meaning": "present participle of unbind",
                  "examples": []
                }
              ]
            }
          ]
        }
      ],
      "letter": [],
      "number": []
    }
  ]
}