{
  "word": "searcheress",
  "etymologies": [
    {
      "description": [
        "searcher +‎ -ess"
      ],
      "adjectives": [],
      "adverbs": [],
      "nouns": [
        {
          "description": "searcheress (plural searcheresses)",
          "definitionGroups": [
            {
              "group": null,
              "entries": [
                {
                  "meaning": "(archaic) A female searcher.",
                  "examples": []
                }
              ]
            }
          ]
        }
      ],
      "prepositions": [],
      "verbs": [],
      "letter": [],
      "number": []
    }
  ]
}