{
  "word": "suppeditation",
  "etymologies": [
    {
      "description": [
        "From Latin suppeditatio."
      ],
      "adjectives": [],
      "adverbs": [],
      "nouns": [
        {
          "description": "suppeditation (usually uncountable, plural suppeditations)",
          "definitionGroups": [
            {
              "group": null,
              "entries": [
                {
                  "meaning": "(obsolete, rare) supply; aid afforded",
                  "examples": [
                    "I cannot sufficiently marvel that this part of knowledge  […]  should be omitted both in morality and policy; considering it is of so great ministry and suppeditation to them both."
                  ]
                }
              ]
            }
          ]
        }
      ],
      "prepositions": [],
      "verbs": [],
      "letter": [],
      "number": []
    }
  ]
}