{
  "word": "tyne",
  "etymologies": [
    {
      "description": [
        "See teen."
      ],
      "adjectives": [],
      "adverbs": [],
      "nouns": [
        {
          "description": "tyne",
          "definitionGroups": [
            {
              "group": null,
              "entries": [
                {
                  "meaning": "(obsolete) anxiety; teen",
                  "examples": []
                }
              ]
            }
          ]
        }
      ],
      "prepositions": [],
      "verbs": [
        {
          "description": "tyne (third-person singular simple present tynes, present participle tyning, simple past and past participle tyned)",
          "definitionGroups": [
            {
              "group": null,
              "entries": [
                {
                  "meaning": "(transitive, obsolete) To lose.",
                  "examples": [
                    "‘Yes, bonny wee thing, I’ll wear you in my bosom, lest my jewel I should tyne.’"
                  ]
                }
              ]
            },
            {
              "group": null,
              "entries": [
                {
                  "meaning": "(intransitive, obsolete) To become lost; to perish.",
                  "examples": []
                }
              ]
            }
          ]
        }
      ],
      "letter": [],
      "number": []
    },
    {
      "description": [],
      "adjectives": [],
      "adverbs": [],
      "nouns": [
        {
          "description": "tyne (plural tynes)",
          "definitionGroups": [
            {
              "group": null,
              "entries": [
                {
                  "meaning": "Alternative form of tine",
                  "examples": []
                }
              ]
            }
          ]
        }
      ],
      "prepositions": [],
      "verbs": [],
      "letter": [],
      "number": []
    }
  ]
}