{
  "word": "unshakable",
  "etymologies": [
    {
      "description": [
        "From un- +‎ shake +‎ -able."
      ],
      "adjectives": [
        {
          "description": "unshakable (comparative more unshakable, superlative most unshakable)",
          "definitionGroups": [
            {
              "group": null,
              "entries": [
                {
                  "meaning": "Not able to be shaken; firm, solid",
                  "examples": [
                    "Antonym: shakable"
                  ]
                }
              ]
            },
            {
              "group": null,
              "entries": [
                {
                  "meaning": "resolute, unfaltering, unwavering",
                  "examples": []
                }
              ]
            },
            {
              "group": null,
              "entries": [
                {
                  "meaning": "(figuratively) Having no errors or loopholes; unassailable",
                  "examples": []
                }
              ]
            }
          ]
        }
      ],
      "adverbs": [],
      "nouns": [],
      "prepositions": [],
      "verbs": [],
      "letter": [],
      "number": []
    }
  ]
}