{
  "word": "marquetry",
  "etymologies": [
    {
      "description": [
        "From Middle French marqueterie."
      ],
      "adjectives": [],
      "adverbs": [],
      "nouns": [
        {
          "description": "marquetry (countable and uncountable, plural marquetries)",
          "definitionGroups": [
            {
              "group": null,
              "entries": [
                {
                  "meaning": "(uncountable, woodworking) A decorative technique in which veneers of wood, ivory, metal etc. are inlaid into a wooden surface to form intricate designs.",
                  "examples": [
                    "strawen marquetry"
                  ]
                }
              ]
            },
            {
              "group": null,
              "entries": [
                {
                  "meaning": "(countable) An example of this work.",
                  "examples": []
                }
              ]
            }
          ]
        }
      ],
      "prepositions": [],
      "verbs": [],
      "letter": [],
      "number": []
    }
  ]
}