{
  "word": "unsporting",
  "etymologies": [
    {
      "description": [
        "un- +‎ sporting"
      ],
      "adjectives": [
        {
          "description": "unsporting (comparative more unsporting, superlative most unsporting)",
          "definitionGroups": [
            {
              "group": null,
              "entries": [
                {
                  "meaning": "unfair, or not sportsmanlike",
                  "examples": []
                }
              ]
            }
          ]
        }
      ],
      "adverbs": [],
      "nouns": [],
      "prepositions": [],
      "verbs": []
    }
  ]
}