{
  "word": "preterlegal",
  "etymologies": [
    {
      "description": [
        "preter- +‎ legal"
      ],
      "adjectives": [
        {
          "description": "preterlegal (comparative more preterlegal, superlative most preterlegal)",
          "definitionGroups": [
            {
              "group": null,
              "entries": [
                {
                  "meaning": "Exceeding the limits of law.",
                  "examples": []
                }
              ]
            }
          ]
        }
      ],
      "adverbs": [],
      "nouns": [],
      "prepositions": [],
      "verbs": []
    }
  ]
}