{
  "word": "ngaio",
  "etymologies": [
    {
      "description": [
        "Borrowed from Maori."
      ],
      "adjectives": [],
      "adverbs": [],
      "nouns": [
        {
          "description": "ngaio (plural ngaios)",
          "definitionGroups": [
            {
              "group": null,
              "entries": [
                {
                  "meaning": "An evergreen tree, Myoporum laetum, native to New Zealand.",
                  "examples": []
                }
              ]
            }
          ]
        }
      ],
      "prepositions": [],
      "verbs": [],
      "letter": [],
      "number": []
    }
  ]
}