{
  "word": "pelted",
  "etymologies": [
    {
      "description": [],
      "adjectives": [
        {
          "description": "pelted (not comparable)",
          "definitionGroups": [
            {
              "group": null,
              "entries": [
                {
                  "meaning": "(in combination) Having a specified kind of pelt.",
                  "examples": [
                    "The sleek, black-pelted werewolf was pounding towards them."
                  ]
                }
              ]
            }
          ]
        }
      ],
      "adverbs": [],
      "nouns": [],
      "prepositions": [],
      "verbs": [
        {
          "description": "pelted",
          "definitionGroups": [
            {
              "group": null,
              "entries": [
                {
                  "meaning": "simple past tense and past participle of pelt",
                  "examples": []
                }
              ]
            }
          ]
        }
      ]
    }
  ]
}