{
  "word": "degeneration",
  "etymologies": [
    {
      "description": [
        "From French dégénération, from Latin dēgenerātiō."
      ],
      "adjectives": [],
      "adverbs": [],
      "nouns": [
        {
          "description": "degeneration (usually uncountable, plural degenerations)",
          "definitionGroups": [
            {
              "group": null,
              "entries": [
                {
                  "meaning": "(uncountable, countable) The process or state of growing worse, or the state of having become worse.",
                  "examples": []
                }
              ]
            },
            {
              "group": null,
              "entries": [
                {
                  "meaning": "(uncountable) That condition of a tissue or an organ in which its vitality has become either diminished or perverted; a substitution of a lower for a higher form of structure.",
                  "examples": [
                    "fatty degeneration of the liver"
                  ]
                }
              ]
            },
            {
              "group": null,
              "entries": [
                {
                  "meaning": "(uncountable) Gradual deterioration, from natural causes, of any class of animals or plants or any particular organ or organs; hereditary degradation of type.",
                  "examples": []
                }
              ]
            },
            {
              "group": null,
              "entries": [
                {
                  "meaning": "(countable) A thing that has degenerated.",
                  "examples": []
                }
              ]
            }
          ]
        }
      ],
      "prepositions": [],
      "verbs": [],
      "letter": [],
      "number": []
    }
  ]
}