{
  "word": "vinestalk",
  "etymologies": [
    {
      "description": [
        "vine +‎ stalk"
      ],
      "adjectives": [],
      "adverbs": [],
      "nouns": [
        {
          "description": "vinestalk (plural vinestalks)",
          "definitionGroups": [
            {
              "group": null,
              "entries": [
                {
                  "meaning": "The stalk of a vine.",
                  "examples": []
                }
              ]
            }
          ]
        }
      ],
      "prepositions": [],
      "verbs": [],
      "letter": [],
      "number": []
    }
  ]
}