{
  "word": "nonzealous",
  "etymologies": [
    {
      "description": [
        "non- +‎ zealous"
      ],
      "adjectives": [
        {
          "description": "nonzealous (not comparable)",
          "definitionGroups": [
            {
              "group": null,
              "entries": [
                {
                  "meaning": "Not zealous.",
                  "examples": []
                }
              ]
            }
          ]
        }
      ],
      "adverbs": [],
      "nouns": [],
      "prepositions": [],
      "verbs": []
    }
  ]
}