{
  "word": "nondecane",
  "etymologies": [
    {
      "description": [
        "Latin [Term?], after the number of carbon atoms in the molecule."
      ],
      "adjectives": [],
      "adverbs": [],
      "nouns": [
        {
          "description": "nondecane",
          "definitionGroups": [
            {
              "group": null,
              "entries": [
                {
                  "meaning": "(chemistry) A hydrocarbon of the paraffin series, C19H40.",
                  "examples": []
                }
              ]
            }
          ]
        }
      ],
      "prepositions": [],
      "verbs": []
    }
  ]
}