{
  "word": "obligatos",
  "etymologies": [
    {
      "description": [],
      "adjectives": [],
      "adverbs": [],
      "nouns": [
        {
          "description": "obligatos",
          "definitionGroups": [
            {
              "group": null,
              "entries": [
                {
                  "meaning": "plural of obligato",
                  "examples": []
                }
              ]
            }
          ]
        }
      ],
      "prepositions": [],
      "verbs": []
    }
  ]
}