{
  "word": "ecstasize",
  "etymologies": [
    {
      "description": [
        "ecstasy +‎ -ize"
      ],
      "adjectives": [],
      "adverbs": [],
      "nouns": [],
      "prepositions": [],
      "verbs": [
        {
          "description": "ecstasize (third-person singular simple present ecstasizes, present participle ecstasizing, simple past and past participle ecstasized)",
          "definitionGroups": [
            {
              "group": null,
              "entries": [
                {
                  "meaning": "(intransitive) To go into a state of ecstasy or rapture.",
                  "examples": []
                }
              ]
            },
            {
              "group": null,
              "entries": [
                {
                  "meaning": "(transitive) To send into a state of ecstasy.",
                  "examples": []
                }
              ]
            }
          ]
        }
      ],
      "letter": [],
      "number": []
    }
  ]
}