{
  "word": "lemel",
  "etymologies": [
    {
      "description": [
        "From Middle English lymail, from Anglo-Norman limaille, from Latin limare, a form of limo (“to file”); see further there."
      ],
      "adjectives": [],
      "adverbs": [],
      "nouns": [
        {
          "description": "lemel (countable and uncountable, plural lemels)",
          "definitionGroups": [
            {
              "group": null,
              "entries": [
                {
                  "meaning": "metal filings",
                  "examples": []
                }
              ]
            }
          ]
        }
      ],
      "prepositions": [],
      "verbs": [],
      "letter": [],
      "number": []
    }
  ]
}