{
  "word": "efficaciousness",
  "etymologies": [
    {
      "description": [
        "efficacious +‎ -ness"
      ],
      "adjectives": [],
      "adverbs": [],
      "nouns": [
        {
          "description": "efficaciousness (uncountable)",
          "definitionGroups": [
            {
              "group": null,
              "entries": [
                {
                  "meaning": "Quality of being efficacious.",
                  "examples": []
                }
              ]
            }
          ]
        }
      ],
      "prepositions": [],
      "verbs": [],
      "letter": [],
      "number": []
    }
  ]
}