{
  "word": "cladoceran",
  "etymologies": [
    {
      "description": [
        "Cladocera  +‎ -an"
      ],
      "adjectives": [],
      "adverbs": [],
      "nouns": [
        {
          "description": "cladoceran (plural cladocerans)",
          "definitionGroups": [
            {
              "group": null,
              "entries": [
                {
                  "meaning": "Any of the small crustaceans of the order Cladocera",
                  "examples": []
                }
              ]
            }
          ]
        }
      ],
      "prepositions": [],
      "verbs": [],
      "letter": [],
      "number": []
    }
  ]
}