{
  "word": "tonally",
  "etymologies": [
    {
      "description": [
        "tonal +‎ -ly"
      ],
      "adjectives": [],
      "adverbs": [
        {
          "description": "tonally (comparative more tonally, superlative most tonally)",
          "definitionGroups": [
            {
              "group": null,
              "entries": [
                {
                  "meaning": "In a tonal manner.",
                  "examples": []
                }
              ]
            },
            {
              "group": null,
              "entries": [
                {
                  "meaning": "Regarding tone.",
                  "examples": []
                }
              ]
            }
          ]
        }
      ],
      "nouns": [],
      "prepositions": [],
      "verbs": [],
      "letter": [],
      "number": []
    }
  ]
}