{
  "word": "latticewise",
  "etymologies": [
    {
      "description": [
        "lattice +‎ -wise"
      ],
      "adjectives": [],
      "adverbs": [
        {
          "description": "latticewise (not comparable)",
          "definitionGroups": [
            {
              "group": null,
              "entries": [
                {
                  "meaning": "In a lattice arrangement.",
                  "examples": []
                }
              ]
            }
          ]
        }
      ],
      "nouns": [],
      "prepositions": [],
      "verbs": [],
      "letter": [],
      "number": []
    }
  ]
}