{
  "word": "conicality",
  "etymologies": [
    {
      "description": [
        "conical +‎ -ity"
      ],
      "adjectives": [],
      "adverbs": [],
      "nouns": [
        {
          "description": "conicality (uncountable)",
          "definitionGroups": [
            {
              "group": null,
              "entries": [
                {
                  "meaning": "The condition of being conical",
                  "examples": []
                }
              ]
            }
          ]
        }
      ],
      "prepositions": [],
      "verbs": [],
      "letter": [],
      "number": []
    }
  ]
}