{
  "word": "starchiness",
  "etymologies": [
    {
      "description": [
        "starchy +‎ -ness"
      ],
      "adjectives": [],
      "adverbs": [],
      "nouns": [
        {
          "description": "starchiness (uncountable)",
          "definitionGroups": [
            {
              "group": null,
              "entries": [
                {
                  "meaning": "The property of being starchy.",
                  "examples": [
                    "Some people on diets avoid potatoes because of their starchiness.",
                    "The starchiness of the freshly pressed shirt made it very uncomfortable."
                  ]
                }
              ]
            }
          ]
        }
      ],
      "prepositions": [],
      "verbs": [],
      "letter": [],
      "number": []
    }
  ]
}