{
  "word": "panchway",
  "etymologies": [
    {
      "description": [
        "From Bengali পানসি (pansi, “pinnace”), from English pinnace."
      ],
      "adjectives": [],
      "adverbs": [],
      "nouns": [
        {
          "description": "panchway (plural panchways)",
          "definitionGroups": [
            {
              "group": null,
              "entries": [
                {
                  "meaning": "(India, now historical) A Bengalese four-oared passenger boat. [from 18th c.]",
                  "examples": [
                    "[A] Bengal boat called a paunceway came alongside, which Colonel Watson engaged to convey him to Calcutta."
                  ]
                }
              ]
            }
          ]
        }
      ],
      "prepositions": [],
      "verbs": []
    }
  ]
}