{
  "word": "retecious",
  "etymologies": [
    {
      "description": [
        "From Latin rete (“a net”)."
      ],
      "adjectives": [
        {
          "description": "retecious (comparative more retecious, superlative most retecious)",
          "definitionGroups": [
            {
              "group": null,
              "entries": [
                {
                  "meaning": "Resembling netting; retiform.",
                  "examples": []
                }
              ]
            }
          ]
        }
      ],
      "adverbs": [],
      "nouns": [],
      "prepositions": [],
      "verbs": [],
      "letter": [],
      "number": []
    }
  ]
}