{
  "word": "receivedness",
  "etymologies": [
    {
      "description": [
        "received +‎ -ness"
      ],
      "adjectives": [],
      "adverbs": [],
      "nouns": [
        {
          "description": "receivedness (uncountable)",
          "definitionGroups": [
            {
              "group": null,
              "entries": [
                {
                  "meaning": "The state or quality of being received, accepted, or current.",
                  "examples": [
                    "the receivedness of an opinion"
                  ]
                }
              ]
            }
          ]
        }
      ],
      "prepositions": [],
      "verbs": [],
      "letter": [],
      "number": []
    }
  ]
}