{
  "word": "oversetting",
  "etymologies": [
    {
      "description": [],
      "adjectives": [],
      "adverbs": [],
      "nouns": [],
      "prepositions": [],
      "verbs": [
        {
          "description": "oversetting",
          "definitionGroups": [
            {
              "group": null,
              "entries": [
                {
                  "meaning": "present participle of overset",
                  "examples": []
                }
              ]
            }
          ]
        }
      ]
    }
  ]
}