{
  "word": "ragger",
  "etymologies": [
    {
      "description": [
        "rag +‎ -er"
      ],
      "adjectives": [],
      "adverbs": [],
      "nouns": [
        {
          "description": "ragger (plural raggers)",
          "definitionGroups": [
            {
              "group": null,
              "entries": [
                {
                  "meaning": "A toy for dogs, resembling intertwined strands of rope.",
                  "examples": []
                }
              ]
            },
            {
              "group": null,
              "entries": [
                {
                  "meaning": "(Britain) an annoying person, especially a noisy one, one who rags upon another",
                  "examples": []
                }
              ]
            }
          ]
        }
      ],
      "prepositions": [],
      "verbs": [],
      "letter": [],
      "number": []
    }
  ]
}