{
  "word": "schismatically",
  "etymologies": [
    {
      "description": [
        "schismatic +‎ -ally"
      ],
      "adjectives": [],
      "adverbs": [
        {
          "description": "schismatically (comparative more schismatically, superlative most schismatically)",
          "definitionGroups": [
            {
              "group": null,
              "entries": [
                {
                  "meaning": "In a schismatic way.",
                  "examples": []
                }
              ]
            }
          ]
        }
      ],
      "nouns": [],
      "prepositions": [],
      "verbs": [],
      "letter": [],
      "number": []
    }
  ]
}