{
  "word": "coning",
  "etymologies": [
    {
      "description": [],
      "adjectives": [],
      "adverbs": [],
      "nouns": [],
      "prepositions": [],
      "verbs": [
        {
          "description": "coning",
          "definitionGroups": [
            {
              "group": null,
              "entries": [
                {
                  "meaning": "present participle of cone",
                  "examples": []
                }
              ]
            }
          ]
        }
      ],
      "letter": [],
      "number": []
    }
  ]
}