{
  "word": "linkable",
  "etymologies": [
    {
      "description": [
        "link +‎ -able"
      ],
      "adjectives": [
        {
          "description": "linkable (not comparable)",
          "definitionGroups": [
            {
              "group": null,
              "entries": [
                {
                  "meaning": "Capable of being linked.",
                  "examples": [
                    "The evidence found at the crime scene was not linkable to the primary suspect."
                  ]
                }
              ]
            }
          ]
        }
      ],
      "adverbs": [],
      "nouns": [],
      "prepositions": [],
      "verbs": [],
      "letter": [],
      "number": []
    }
  ]
}