{
  "word": "mentalization",
  "etymologies": [
    {
      "description": [
        "mental +‎ -ization"
      ],
      "adjectives": [],
      "adverbs": [],
      "nouns": [
        {
          "description": "mentalization (usually uncountable, plural mentalizations)",
          "definitionGroups": [
            {
              "group": null,
              "entries": [
                {
                  "meaning": "(psychology) The ability to understand mental states that underlies the overt behaviour of oneself or others.",
                  "examples": []
                }
              ]
            }
          ]
        }
      ],
      "prepositions": [],
      "verbs": [],
      "letter": [],
      "number": []
    }
  ]
}