{
  "word": "unextenuating",
  "etymologies": [
    {
      "description": [
        "un- +‎ extenuating"
      ],
      "adjectives": [
        {
          "description": "unextenuating",
          "definitionGroups": [
            {
              "group": null,
              "entries": [
                {
                  "meaning": "Not extenuating.",
                  "examples": []
                }
              ]
            }
          ]
        }
      ],
      "adverbs": [],
      "nouns": [],
      "prepositions": [],
      "verbs": [],
      "letter": [],
      "number": []
    }
  ]
}