{
  "word": "plagiaristically",
  "etymologies": [
    {
      "description": [
        "plagiaristic +‎ -ally"
      ],
      "adjectives": [],
      "adverbs": [
        {
          "description": "plagiaristically (comparative more plagiaristically, superlative most plagiaristically)",
          "definitionGroups": [
            {
              "group": null,
              "entries": [
                {
                  "meaning": "In a plagiaristic manner.",
                  "examples": []
                }
              ]
            }
          ]
        }
      ],
      "nouns": [],
      "prepositions": [],
      "verbs": []
    }
  ]
}