{
  "word": "clarets",
  "etymologies": [
    {
      "description": [],
      "adjectives": [],
      "adverbs": [],
      "nouns": [
        {
          "description": "clarets",
          "definitionGroups": [
            {
              "group": null,
              "entries": [
                {
                  "meaning": "plural of claret",
                  "examples": []
                }
              ]
            }
          ]
        }
      ],
      "prepositions": [],
      "verbs": [],
      "letter": [],
      "number": []
    }
  ]
}