{
  "word": "representative",
  "etymologies": [
    {
      "description": [
        "From Middle English (implied in representatyfliche), from Old French representatif. By surface analysis, represent +‎ -ative; See representation."
      ],
      "adjectives": [
        {
          "description": "representative (comparative more representative, superlative most representative)",
          "definitionGroups": [
            {
              "group": null,
              "entries": [
                {
                  "meaning": "Typical; having the same properties or interest as a larger group.",
                  "examples": [
                    "If you took all the fools out of the legislature, it wouldn't be a representative body anymore."
                  ]
                }
              ]
            },
            {
              "group": null,
              "entries": [
                {
                  "meaning": "Representing, showing a likeness.",
                  "examples": [
                    "Are you sure this paper is representative of your child's writing?",
                    "the representative faculty of the human imagination"
                  ]
                }
              ]
            }
          ]
        }
      ],
      "adverbs": [],
      "nouns": [
        {
          "description": "representative (plural representatives)",
          "definitionGroups": [
            {
              "group": "A delegate.",
              "entries": [
                {
                  "meaning": "Someone who represents others as a member of a legislative or governing body. [from 17th c.]",
                  "examples": [
                    "She served four terms as representative of her local at the national union convention."
                  ]
                },
                {
                  "meaning": "One who speaks for or acts on behalf of another in a particular (especially official) capacity. [from 17th c.]",
                  "examples": [
                    "I will send a representative to work out the details of the contract."
                  ]
                },
                {
                  "meaning": "(law) An heir. [from 17th c.]",
                  "examples": []
                },
                {
                  "meaning": "(US, politics) Specifically, a member of the United States House of Representatives. [from 18th c.]",
                  "examples": [
                    "All representatives face re-election every two years."
                  ]
                },
                {
                  "meaning": "A company agent who visits potential purchasers; a salesman. [from 20th c.]",
                  "examples": []
                }
              ]
            },
            {
              "group": "Something standing for something else.",
              "entries": [
                {
                  "meaning": "Something representing or standing for another; a symbol, an embodiment. [from 17th c.]",
                  "examples": []
                },
                {
                  "meaning": "A member of a particular class.",
                  "examples": []
                },
                {
                  "meaning": "Something (especially a living organism) regarded as typical of its class; a type. [from 17th c.]",
                  "examples": []
                },
                {
                  "meaning": "A substitute or analogue. [from 17th c.]",
                  "examples": []
                }
              ]
            }
          ]
        }
      ],
      "prepositions": [],
      "verbs": [],
      "letter": [],
      "number": []
    }
  ]
}