{
  "word": "antihidrotic",
  "etymologies": [
    {
      "description": [
        "anti- +‎ hidrotic"
      ],
      "adjectives": [
        {
          "description": "antihidrotic (not comparable)",
          "definitionGroups": [
            {
              "group": null,
              "entries": [
                {
                  "meaning": "Countering hidrosis.",
                  "examples": []
                }
              ]
            }
          ]
        }
      ],
      "adverbs": [],
      "nouns": [
        {
          "description": "antihidrotic (plural antihidrotics)",
          "definitionGroups": [
            {
              "group": null,
              "entries": [
                {
                  "meaning": "Any drug that counters hidrosis.",
                  "examples": []
                }
              ]
            }
          ]
        }
      ],
      "prepositions": [],
      "verbs": [],
      "letter": [],
      "number": []
    }
  ]
}